csdl2.pyd
_csdl2test.pyd
pycsdl2-2.0.0.0.dev5.data/headers/begin_code.h
pycsdl2-2.0.0.0.dev5.data/headers/close_code.h
pycsdl2-2.0.0.0.dev5.data/headers/csdl2.pxd
pycsdl2-2.0.0.0.dev5.data/headers/pycsdl2.h
pycsdl2-2.0.0.0.dev5.data/headers/SDL.h
pycsdl2-2.0.0.0.dev5.data/headers/SDL_assert.h
pycsdl2-2.0.0.0.dev5.data/headers/SDL_atomic.h
pycsdl2-2.0.0.0.dev5.data/headers/SDL_audio.h
pycsdl2-2.0.0.0.dev5.data/headers/SDL_bits.h
pycsdl2-2.0.0.0.dev5.data/headers/SDL_blendmode.h
pycsdl2-2.0.0.0.dev5.data/headers/SDL_clipboard.h
pycsdl2-2.0.0.0.dev5.data/headers/SDL_config.h
pycsdl2-2.0.0.0.dev5.data/headers/SDL_config_android.h
pycsdl2-2.0.0.0.dev5.data/headers/SDL_config_iphoneos.h
pycsdl2-2.0.0.0.dev5.data/headers/SDL_config_macosx.h
pycsdl2-2.0.0.0.dev5.data/headers/SDL_config_minimal.h
pycsdl2-2.0.0.0.dev5.data/headers/SDL_config_pandora.h
pycsdl2-2.0.0.0.dev5.data/headers/SDL_config_psp.h
pycsdl2-2.0.0.0.dev5.data/headers/SDL_config_windows.h
pycsdl2-2.0.0.0.dev5.data/headers/SDL_config_wiz.h
pycsdl2-2.0.0.0.dev5.data/headers/SDL_copying.h
pycsdl2-2.0.0.0.dev5.data/headers/SDL_cpuinfo.h
pycsdl2-2.0.0.0.dev5.data/headers/SDL_endian.h
pycsdl2-2.0.0.0.dev5.data/headers/SDL_error.h
pycsdl2-2.0.0.0.dev5.data/headers/SDL_events.h
pycsdl2-2.0.0.0.dev5.data/headers/SDL_gamecontroller.h
pycsdl2-2.0.0.0.dev5.data/headers/SDL_gesture.h
pycsdl2-2.0.0.0.dev5.data/headers/SDL_haptic.h
pycsdl2-2.0.0.0.dev5.data/headers/SDL_hints.h
pycsdl2-2.0.0.0.dev5.data/headers/SDL_joystick.h
pycsdl2-2.0.0.0.dev5.data/headers/SDL_keyboard.h
pycsdl2-2.0.0.0.dev5.data/headers/SDL_keycode.h
pycsdl2-2.0.0.0.dev5.data/headers/SDL_loadso.h
pycsdl2-2.0.0.0.dev5.data/headers/SDL_log.h
pycsdl2-2.0.0.0.dev5.data/headers/SDL_main.h
pycsdl2-2.0.0.0.dev5.data/headers/SDL_messagebox.h
pycsdl2-2.0.0.0.dev5.data/headers/SDL_mouse.h
pycsdl2-2.0.0.0.dev5.data/headers/SDL_mutex.h
pycsdl2-2.0.0.0.dev5.data/headers/SDL_name.h
pycsdl2-2.0.0.0.dev5.dist-info/DESCRIPTION.rst
pycsdl2-2.0.0.0.dev5.dist-info/METADATA
pycsdl2-2.0.0.0.dev5.dist-info/metadata.json
pycsdl2-2.0.0.0.dev5.dist-info/RECORD
pycsdl2-2.0.0.0.dev5.dist-info/top_level.txt
pycsdl2-2.0.0.0.dev5.dist-info/WHEEL
